scikit_chem-0.0.6.dist-info/DESCRIPTION.rst
scikit_chem-0.0.6.dist-info/METADATA
scikit_chem-0.0.6.dist-info/RECORD
scikit_chem-0.0.6.dist-info/WHEEL
scikit_chem-0.0.6.dist-info/metadata.json
scikit_chem-0.0.6.dist-info/top_level.txt
skchem/__init__.py
skchem/base.py
skchem/metrics.py
skchem/core/__init__.py
skchem/core/atom.py
skchem/core/base.py
skchem/core/bond.py
skchem/core/conformer.py
skchem/core/mol.py
skchem/core/point.py
skchem/cross_validation/__init__.py
skchem/cross_validation/similarity_threshold.py
skchem/data/__init__.py
skchem/data/converters/__init__.py
skchem/data/converters/base.py
skchem/data/converters/bradley_open_mp.py
skchem/data/converters/bursi_ames.py
skchem/data/converters/diversity_set.py
skchem/data/converters/muller_ames.py
skchem/data/converters/nmrshiftdb2.py
skchem/data/converters/physprop.py
skchem/data/converters/tox21.py
skchem/data/datasets/__init__.py
skchem/data/datasets/base.py
skchem/data/datasets/bradley_open_mp.py
skchem/data/datasets/bursi_ames.py
skchem/data/datasets/diversity_set.py
skchem/data/datasets/muller_ames.py
skchem/data/datasets/nmrshiftdb2.py
skchem/data/datasets/physprop.py
skchem/data/datasets/tox21.py
skchem/data/downloaders/__init__.py
skchem/data/downloaders/base.py
skchem/data/downloaders/bradley_open_mp.py
skchem/data/downloaders/bursi_ames.py
skchem/data/downloaders/diversity.py
skchem/data/downloaders/muller_ames.py
skchem/data/downloaders/nmrshiftdb2.py
skchem/data/downloaders/physprop.py
skchem/data/downloaders/tox21.py
skchem/descriptors/__init__.py
skchem/descriptors/atom.py
skchem/descriptors/chemaxon.py
skchem/descriptors/fingerprints.py
skchem/descriptors/moe.py
skchem/descriptors/physicochemical.py
skchem/filters/__init__.py
skchem/filters/base.py
skchem/filters/simple.py
skchem/filters/smarts.py
skchem/filters/stereo.py
skchem/forcefields/__init__.py
skchem/forcefields/base.py
skchem/forcefields/mmff.py
skchem/forcefields/uff.py
skchem/interact/__init__.py
skchem/interact/desc_vis.py
skchem/io/__init__.py
skchem/io/sdf.py
skchem/io/smiles.py
skchem/pandas_ext/__init__.py
skchem/pandas_ext/structure_methods.py
skchem/pipeline/__init__.py
