Metadata-Version: 2.0
Name: scikit-chem
Version: 0.0.6
Summary: A set of python modules for cheminformatics
Home-page: http://github.com/richlewis42/scikit-chem
Author: Richard Lewis
Author-email: rl403@cam.ac.uk
License: new BSD
Download-URL: https://github.com/richlewis42/scikit-chem/archive/master.zip
Platform: UNKNOWN
Classifier: Development Status:: 2 - Pre - Alpha
Classifier: Intended Audience :: Science/Research
Classifier: Intended Audience :: Developers
Classifier: License :: OSI Approved :: BSD License
Classifier: Natural Language :: English
Classifier: Programming Language :: Python
Classifier: Programming Language :: Python :: 2
Classifier: Programming Language :: Python :: 2.7
Classifier: Programming Language :: Python :: 3
Classifier: Programming Language :: Python :: 3.5
Classifier: Operating System :: Microsoft :: Windows
Classifier: Operating System :: POSIX
Classifier: Operating System :: Unix
Classifier: Operating System :: MacOS
Classifier: Topic :: Software Development
Classifier: Topic :: Scientific/Engineering :: Chemistry
Requires-Dist: fuel
Requires-Dist: h5py
Requires-Dist: ipywidgets
Requires-Dist: matplotlib
Requires-Dist: numpy
Requires-Dist: pandas
Requires-Dist: scikit-learn
Requires-Dist: scipy
